smarturls.py
smarturls-0.1.9.dist-info/METADATA
smarturls-0.1.9.dist-info/RECORD
smarturls-0.1.9.dist-info/WHEEL
smarturls-0.1.9.dist-info/top_level.txt
smarturls-0.1.9.dist-info/zip-safe
