Metadata-Version: 2.1
Name: smarturls
Version: 0.1.9
Summary: A URL construction helper for Django.
Home-page: https://amitu.com/smarturls/
Author: Amit Upadhyay
Author-email: upadhyay@gmail.com
License: BSD
Keywords: helper,django,utils,regex,utility
Platform: UNKNOWN
Classifier: Intended Audience :: Developers
Classifier: Natural Language :: English
Classifier: Operating System :: OS Independent
Classifier: Operating System :: POSIX :: Linux
Classifier: Operating System :: Microsoft :: Windows
Classifier: Operating System :: MacOS :: MacOS X
Classifier: Programming Language :: Python
Classifier: Programming Language :: Python :: 3
Classifier: Programming Language :: Python :: Implementation :: CPython
Classifier: Topic :: Software Development
Requires-Dist: Django (>=1.5)
